vector_cli/__init__.py
vector_cli/app.py
vector_cli/main.py
vector_cli-0.2.0.dist-info/METADATA
vector_cli-0.2.0.dist-info/WHEEL
vector_cli-0.2.0.dist-info/entry_points.txt
vector_cli-0.2.0.dist-info/RECORD
