Metadata-Version: 2.1
Name: vector_cli
Version: 0.2.0
Summary: cli tool to ask about your files
Author: Esa Nuurtamo
Author-email: esa.nuurtamo@gmail.com
Requires-Python: >=3.11,<3.12
Classifier: Programming Language :: Python :: 3
Classifier: Programming Language :: Python :: 3.11
Requires-Dist: click (>=8.0,<9.0)
Requires-Dist: faiss-cpu (>=1.8.0,<2.0.0)
Requires-Dist: langchain (>=0.1.16,<0.2.0)
Requires-Dist: langchain-openai (>=0.1.3,<0.2.0)
Requires-Dist: pypdf (>=4.2.0,<5.0.0)
Requires-Dist: tiktoken (>=0.6.0,<0.7.0)
